{
    "image": {
        "file_name": "frame_984",
        "resolution": [
            3840,
            2160
        ]
    },
    "annotations": {
        "Black_1": [
            [
                1224.0253564453126,
                1044.609591369629
            ],
            [
                1215.1278497314454,
                1064.4982937622071
            ],
            [
                1203.4192391967774,
                1068.51631439209
            ],
            [
                1220.0187646484376,
                1086.4012631225587
            ],
            [
                1192.5375177001954,
                1094.2637203979493
            ],
            [
                1228.7947808837891,
                1107.3626583862306
            ],
            [
                1192.1511193847657,
                1120.6500119018556
            ],
            [
                1200.9677926635743,
                1115.4391201782228
            ],
            [
                1166.0169793701173,
                1180.4872387695314
            ],
            [
                1222.6082727050782,
                1186.1816967773439
            ]
        ],
        "Black_10": [
            [
                2000.4757043457032,
                1075.194557800293
            ],
            [
                2009.2135736083985,
                1095.169884338379
            ],
            [
                2027.5270654296876,
                1088.4330068969728
            ],
            [
                2002.7319387888028,
                1121.9566912960465
            ],
            [
                2021.664287820648,
                1114.4802222516234
            ],
            [
                1985.2466482816847,
                1123.4037498207736
            ],
            [
                2008.520172887711,
                1126.7802197118033
            ],
            [
                2028.1668244934083,
                1144.9336782836915
            ],
            [
                2033.8038903808595,
                1237.9134985351564
            ],
            [
                2011.1762734985352,
                1225.6816259765626
            ]
        ],
        "Black_15": [
            [
                1894.4072998046875,
                1064.021895751953
            ],
            [
                1861.2061813354492,
                1070.9692834472655
            ],
            [
                1886.8890808105468,
                1081.2564691162108
            ],
            [
                1849.5012329101562,
                1095.1648553466796
            ],
            [
                1889.6899688720703,
                1113.652724609375
            ],
            [
                1866.7245986938476,
                1102.157607421875
            ],
            [
                1903.799740600586,
                1116.0486291503905
            ],
            [
                1868.3015296936035,
                1130.9366830444335
            ],
            [
                1856.4927642822265,
                1215.632216796875
            ],
            [
                1908.620785522461,
                1211.1684716796874
            ]
        ],
        "White_0": [
            [
                1963.1954132080077,
                1070.707098388672
            ],
            [
                1966.146531677246,
                1092.2125915527345
            ],
            [
                1990.5799270629882,
                1086.5412353515626
            ],
            [
                1957.2701834702955,
                1122.9213969791979
            ],
            [
                1986.5731185960178,
                1113.3949283580782
            ],
            [
                1935.4437173889962,
                1122.559632348016
            ],
            [
                1974.0319447150503,
                1113.1537519372905
            ],
            [
                1979.3549362182616,
                1141.5351776123048
            ],
            [
                1966.834764099121,
                1230.4652465820313
            ],
            [
                1998.1712966918944,
                1211.8376220703126
            ]
        ],
        "White_9": [
            [
                1529.0113293457032,
                1111.9397720336915
            ],
            [
                1513.450527536974,
                1128.3329113825946
            ],
            [
                1498.3676579295434,
                1138.3881577875484
            ],
            [
                1505.9090927332588,
                1164.7831796005519
            ],
            [
                1494.9111669778408,
                1165.7258589510163
            ],
            [
                1488.9408644248995,
                1185.207898860614
            ],
            [
                1503.7095075821753,
                1191.4924278637102
            ],
            [
                1495.5396198781505,
                1184.2652195101496
            ],
            [
                1482.3421089716485,
                1246.4820566408007
            ],
            [
                1482.3421089716485,
                1259.9937939974573
            ]
        ],
        "White_10": [
            [
                1788.6800476074218,
                1066.8139044189454
            ],
            [
                1781.174951171875,
                1080.238388671875
            ],
            [
                1765.8784576416015,
                1084.9620520019532
            ],
            [
                1781.3846527099608,
                1105.6065985107423
            ],
            [
                1764.4461303710937,
                1115.3999487304689
            ],
            [
                1789.70546875,
                1119.2650915527345
            ],
            [
                1775.9394470214843,
                1138.3998266601564
            ],
            [
                1770.1056190490722,
                1129.1080709838868
            ],
            [
                1779.4882751464843,
                1199.0708471679689
            ],
            [
                1743.8830810546874,
                1202.426376953125
            ]
        ]
    }
}