{
    "image": {
        "file_name": "frame_386",
        "resolution": [
            3840,
            2160
        ]
    },
    "annotations": {
        "Black_1": [
            [
                1963.9597229003907,
                1055.8347387695312
            ],
            [
                1937.1770233154298,
                1057.4376287841797
            ],
            [
                1958.4935363769532,
                1070.7391577148437
            ],
            [
                1906.9369658251185,
                1074.853498016874
            ],
            [
                1945.5107045079017,
                1097.3783089265285
            ],
            [
                1913.1312888252737,
                1094.2811474264508
            ],
            [
                1959.0255910536944,
                1112.582556290545
            ],
            [
                1927.4086669921876,
                1110.6101370239257
            ],
            [
                1929.1802165984022,
                1172.8364254738706
            ],
            [
                1877.0915913698266,
                1183.5357106559563
            ]
        ],
        "Black_10": [
            [
                2273.71587890625,
                1172.6687890625
            ],
            [
                2285.577664794922,
                1196.4305993652345
            ],
            [
                2305.9242529296876,
                1191.1430627441407
            ],
            [
                2281.7947973632813,
                1235.7643395996095
            ],
            [
                2303.2679418945313,
                1230.2616235351563
            ],
            [
                2262.8470892333985,
                1261.37826171875
            ],
            [
                2284.735928955078,
                1250.040859375
            ],
            [
                2298.1039556884766,
                1261.1513787841798
            ],
            [
                2312.3835621988974,
                1352.753352614735
            ],
            [
                2282.5381877436057,
                1357.258314796666
            ]
        ],
        "Black_15": [
            [
                2048.283774108887,
                1064.4189511108398
            ],
            [
                2066.7960345458987,
                1085.4372311401366
            ],
            [
                2058.1167895507815,
                1080.0051327514648
            ],
            [
                2074.7484118652346,
                1117.4061489868163
            ],
            [
                2053.142401428223,
                1111.7012844848632
            ],
            [
                2078.8101794433596,
                1145.6378994750976
            ],
            [
                2042.8378131103516,
                1132.9623165893554
            ],
            [
                2063.7400500488284,
                1137.00130279541
            ],
            [
                2044.728186340332,
                1221.8890209960937
            ],
            [
                2082.5054919433596,
                1223.7844677734374
            ]
        ],
        "White_0": [
            [
                1998.7925827026368,
                1067.2494259643554
            ],
            [
                2021.5795471191407,
                1082.2816220092773
            ],
            [
                2008.0903579711915,
                1079.6559811401366
            ],
            [
                2034.15654296875,
                1108.3508358764648
            ],
            [
                2010.399722290039,
                1109.4897061157226
            ],
            [
                2030.968051147461,
                1134.7423916625976
            ],
            [
                2005.369761657715,
                1133.1453610229491
            ],
            [
                2014.0168563842774,
                1136.3164196777343
            ],
            [
                2015.4523574829102,
                1215.7156811523437
            ],
            [
                2005.1708862304688,
                1209.1339245605468
            ]
        ],
        "White_9": [
            [
                2225.060518798828,
                1146.5574548339844
            ],
            [
                2195.9908471679687,
                1167.2567193603516
            ],
            [
                2233.8467279052734,
                1174.1284997558594
            ],
            [
                2180.5442529296874,
                1196.3118188476562
            ],
            [
                2230.2789483642578,
                1201.6548822021484
            ],
            [
                2175.8268960591176,
                1211.4101641566535
            ],
            [
                2225.099919923987,
                1219.5754081114032
            ],
            [
                2205.883844909668,
                1228.9011361694336
            ],
            [
                2185.1589303588867,
                1313.2357080078125
            ],
            [
                2196.0767236328124,
                1327.4278466796875
            ]
        ],
        "White_10": [
            [
                1810.9249593227169,
                1176.77826738306
            ],
            [
                1808.954038368122,
                1206.6236418383521
            ],
            [
                1838.2362925506727,
                1196.4874769290077
            ],
            [
                1822.7504850502853,
                1234.77965547542
            ],
            [
                1855.6930210056548,
                1229.9931331571186
            ],
            [
                1812.3327600045702,
                1264.6250299307121
            ],
            [
                1837.6731722779314,
                1239.5661777937216
            ],
            [
                1848.3724574600174,
                1260.6831880215227
            ],
            [
                1822.187364777544,
                1361.7632769785967
            ],
            [
                1871.1788285060422,
                1369.6469607969757
            ]
        ]
    }
}