{
    "image": {
        "file_name": "frame_34",
        "resolution": [
            3840,
            2160
        ]
    },
    "annotations": {
        "Black_1": [
            [
                1942.1234100341796,
                1217.4524853515625
            ],
            [
                1963.7182586669921,
                1237.5525067138672
            ],
            [
                1916.413021850586,
                1233.1333325195312
            ],
            [
                1975.018002319336,
                1276.0884106445312
            ],
            [
                1902.890690612793,
                1269.0981762695312
            ],
            [
                1976.1621826171875,
                1313.2800915527343
            ],
            [
                1899.039273071289,
                1302.7205212402343
            ],
            [
                1931.7851455688476,
                1310.4949200439453
            ],
            [
                1947.5444915771484,
                1411.0237133789062
            ],
            [
                1902.523793029785,
                1404.8606884765625
            ]
        ],
        "Black_10": [
            [
                2174.824445800781,
                1170.3655450439453
            ],
            [
                2198.23625,
                1184.9492700195312
            ],
            [
                2153.2020932006835,
                1183.2167108154297
            ],
            [
                2206.8013134765624,
                1216.7901818847656
            ],
            [
                2142.5109921264648,
                1215.1385095214844
            ],
            [
                2200.6281719970702,
                1244.285863647461
            ],
            [
                2142.0282803344726,
                1246.9786431884766
            ],
            [
                2173.3882580566406,
                1251.4917962646484
            ],
            [
                2181.617872314453,
                1348.5776879882812
            ],
            [
                2152.1021710205077,
                1347.03294921875
            ]
        ],
        "Black_15": [
            [
                1502.320245361328,
                1118.7914831542969
            ],
            [
                1512.8138366699218,
                1130.2966101074219
            ],
            [
                1480.4656005859374,
                1140.4259130859375
            ],
            [
                1512.8877502441405,
                1161.5169775390625
            ],
            [
                1474.7432647705077,
                1176.0207006835938
            ],
            [
                1514.2854248046874,
                1188.5152990722656
            ],
            [
                1478.9169479370116,
                1208.4800207519531
            ],
            [
                1501.8239685058593,
                1197.4383642578125
            ],
            [
                1526.2891021728515,
                1289.0796911621094
            ],
            [
                1485.968896484375,
                1289.8660986328125
            ]
        ],
        "White_0": [
            [
                2453.069826660156,
                1314.3638037109374
            ],
            [
                2466.2014947509765,
                1347.6584509277343
            ],
            [
                2494.049532470703,
                1333.7872198486327
            ],
            [
                2471.2600732421874,
                1393.0958288574218
            ],
            [
                2504.1734643554687,
                1378.2998999023437
            ],
            [
                2448.3782067871093,
                1426.6003759765624
            ],
            [
                2482.840059814453,
                1403.6148413085937
            ],
            [
                2489.944979248047,
                1422.6794927978515
            ],
            [
                2499.298250732422,
                1557.979190673828
            ],
            [
                2493.896166381836,
                1534.2839086914062
            ]
        ],
        "White_9": [
            [
                1917.1290826416016,
                1456.3793896484376
            ],
            [
                1906.0152062988282,
                1502.2726391601564
            ],
            [
                1962.0031365966797,
                1486.032587890625
            ],
            [
                1889.781548461914,
                1547.0275219726564
            ],
            [
                1976.6856927490235,
                1528.2189892578126
            ],
            [
                1858.6134114820156,
                1536.918846848728
            ],
            [
                1949.7704095458985,
                1528.4215344238282
            ],
            [
                1950.3850106811524,
                1582.6130780029298
            ],
            [
                1917.639183959961,
                1726.5077160644532
            ],
            [
                1983.5223626708985,
                1707.9757336425782
            ]
        ],
        "White_10": [
            [
                1143.9807482910155,
                1245.1059240722657
            ],
            [
                1146.5027056884765,
                1257.7778448486329
            ],
            [
                1116.4114428710936,
                1272.1828588867188
            ],
            [
                1149.9822589111327,
                1291.0256018066407
            ],
            [
                1111.3428698730468,
                1310.5888037109376
            ],
            [
                1157.7061663818358,
                1319.4496435546876
            ],
            [
                1122.1724291992186,
                1345.1303076171876
            ],
            [
                1134.6861849975585,
                1334.6078466796876
            ],
            [
                1128.2502032470702,
                1418.9029211425782
            ],
            [
                1134.6159411621093,
                1444.8817724609376
            ]
        ]
    }
}