{
    "image": {
        "file_name": "frame_464",
        "resolution": [
            3840,
            2160
        ]
    },
    "annotations": {
        "Black_1": [
            [
                2597.479107666016,
                1136.1845901489257
            ],
            [
                2622.588726806641,
                1153.3616073608398
            ],
            [
                2584.4163711547853,
                1155.4331100463867
            ],
            [
                2630.8347137451174,
                1179.1340225219726
            ],
            [
                2571.2166412353517,
                1184.323109436035
            ],
            [
                2638.150067138672,
                1200.6571548461914
            ],
            [
                2581.0976684570314,
                1210.1966903686523
            ],
            [
                2606.214131164551,
                1218.654866027832
            ],
            [
                2615.2837036132814,
                1300.3769958496093
            ],
            [
                2572.2684524536135,
                1272.651318359375
            ]
        ],
        "Black_10": [
            [
                1990.63118560791,
                1220.5587719726564
            ],
            [
                1952.4673062133788,
                1239.4855603027345
            ],
            [
                1984.1723233032226,
                1247.2511547851564
            ],
            [
                1944.3988247680663,
                1253.3166455078126
            ],
            [
                1990.569906311035,
                1287.7434033203126
            ],
            [
                1961.9108944702148,
                1240.2765454101564
            ],
            [
                2005.107976989746,
                1319.3220776367189
            ],
            [
                1964.888120727539,
                1317.6048687744142
            ],
            [
                1938.7907925415038,
                1423.2358349609376
            ],
            [
                2021.751546936035,
                1415.545740966797
            ]
        ],
        "Black_15": [
            [
                1927.3890533447266,
                1111.2871240234374
            ],
            [
                1928.5819396972656,
                1128.8159020996093
            ],
            [
                1894.7860412597656,
                1130.4683068847655
            ],
            [
                1929.6698150634766,
                1152.1914208984374
            ],
            [
                1882.789176940918,
                1161.4435876464843
            ],
            [
                1931.324203491211,
                1175.863448486328
            ],
            [
                1886.7845458984375,
                1192.0461419677733
            ],
            [
                1906.7620315551758,
                1187.979758605957
            ],
            [
                1912.558723449707,
                1257.063155517578
            ],
            [
                1878.541488647461,
                1260.9014428710936
            ]
        ],
        "White_0": [
            [
                1953.847131652832,
                1096.9176119995118
            ],
            [
                1955.5357302856446,
                1111.3872622680665
            ],
            [
                1929.0767306518555,
                1118.450860900879
            ],
            [
                1950.4645785522462,
                1139.614175720215
            ],
            [
                1923.738687438965,
                1150.4798373413087
            ],
            [
                1954.2874697875977,
                1163.284860534668
            ],
            [
                1929.1963061523438,
                1177.95621673584
            ],
            [
                1936.4413432312012,
                1174.6186846923829
            ],
            [
                1954.7671405739186,
                1242.1719462135043
            ],
            [
                1892.485331985443,
                1247.3394325156048
            ]
        ],
        "White_9": [
            [
                2435.4494982910155,
                1161.0927255249023
            ],
            [
                2422.809682006836,
                1173.234494934082
            ],
            [
                2407.0280810546874,
                1181.035260925293
            ],
            [
                2414.8215686035155,
                1193.9717538452148
            ],
            [
                2383.892148132324,
                1204.3560006713867
            ],
            [
                2418.6340991210936,
                1216.0349099731445
            ],
            [
                2376.542782897949,
                1235.0419747924805
            ],
            [
                2384.9737979125975,
                1213.1122567749023
            ],
            [
                2413.353459472656,
                1282.7152612304687
            ],
            [
                2374.457417602539,
                1301.904287109375
            ]
        ],
        "White_10": [
            [
                1886.2741424560547,
                1152.7414587402343
            ],
            [
                1877.796176147461,
                1170.387882080078
            ],
            [
                1855.768603515625,
                1177.713809814453
            ],
            [
                1883.3862182617188,
                1196.3405798339843
            ],
            [
                1836.168879699707,
                1204.023349609375
            ],
            [
                1891.6100799560547,
                1214.4862097167968
            ],
            [
                1829.9876358032227,
                1234.618610229492
            ],
            [
                1856.8021041870118,
                1228.0725134277343
            ],
            [
                1844.7730285644532,
                1301.3512915039062
            ],
            [
                1853.99541015625,
                1324.5920141601562
            ]
        ]
    }
}